assets/mdinterface.png
mdinterface/__init__.py
mdinterface/config.py
mdinterface/simulationbox.py
mdinterface/build/__init__.py
mdinterface/build/box.py
mdinterface/build/charges.py
mdinterface/build/continuum2sim.py
mdinterface/build/polymerize.py
mdinterface/build/snippets.py
mdinterface/core/__init__.py
mdinterface/core/polymer.py
mdinterface/core/specie.py
mdinterface/core/topology.py
mdinterface/database/__init__.py
mdinterface/database/graphene.py
mdinterface/database/ions.py
mdinterface/database/metals.py
mdinterface/database/molecules.py
mdinterface/examples/make_box.py
mdinterface/examples/make_polymer.py
mdinterface/examples/make_solvent_box.py
mdinterface/examples/make_specie_ligpargen_resp.py
mdinterface/externals/__init__.py
mdinterface/externals/aimd.py
mdinterface/externals/ligpargen.py
mdinterface/externals/obabel.py
mdinterface/externals/optimization.py
mdinterface/externals/pyscf.py
mdinterface/io/__init__.py
mdinterface/io/lammpswriter.py
mdinterface/io/packmol.py
mdinterface/io/read.py
mdinterface/read/cp2ktraj.py
mdinterface/read/lammpstraj.py
mdinterface/read/read.py
mdinterface/read/trajectory.py
mdinterface/read/xyztraj.py
mdinterface/utils/__init__.py
mdinterface/utils/auxiliary.py
mdinterface/utils/draw.py
mdinterface/utils/graphs.py
mdinterface/utils/map.py
mdinterface/utils/poisson.py
mdinterface/utils/units.py
mdinterface-1.4.0.dist-info/licenses/LICENSE
mdinterface-1.4.0.dist-info/METADATA
mdinterface-1.4.0.dist-info/WHEEL
mdinterface-1.4.0.dist-info/top_level.txt
mdinterface-1.4.0.dist-info/RECORD
