Metadata-Version: 2.4
Name: mdinterface
Version: 1.4.0
Summary: Build Interface Systems for Molecular Dynamics Simulations
Author-email: Fabrice Roncoroni <fabrice.roncoroni@gmail.com>
License-Expression: Apache-2.0
Project-URL: Homepage, https://gitlab.com/roncofaber/mdinterface
Project-URL: Repository, https://gitlab.com/roncofaber/mdinterface.git
Project-URL: Documentation, https://gitlab.com/roncofaber/mdinterface
Project-URL: Bug Tracker, https://gitlab.com/roncofaber/mdinterface/-/issues
Keywords: molecular dynamics,simulation,interface,chemistry,materials science
Classifier: Development Status :: 4 - Beta
Classifier: Intended Audience :: Science/Research
Classifier: Operating System :: OS Independent
Classifier: Programming Language :: Python :: 3
Classifier: Programming Language :: Python :: 3.8
Classifier: Programming Language :: Python :: 3.9
Classifier: Programming Language :: Python :: 3.10
Classifier: Programming Language :: Python :: 3.11
Classifier: Programming Language :: Python :: 3.12
Classifier: Topic :: Scientific/Engineering
Classifier: Topic :: Scientific/Engineering :: Chemistry
Classifier: Topic :: Scientific/Engineering :: Physics
Requires-Python: >=3.8
License-File: LICENSE
Requires-Dist: mdanalysis>=2.0.0
Requires-Dist: ase>=3.22.0
Requires-Dist: numpy>=1.20.0
Requires-Dist: networkx>=2.5
Requires-Dist: platformdirs>=2.0.0
Requires-Dist: configparser>=5.0.0
Requires-Dist: libarvo
Provides-Extra: resp
Requires-Dist: pyscf>=2.0.0; extra == "resp"
Requires-Dist: pymbxas; extra == "resp"
Provides-Extra: aimd
Requires-Dist: fairchem-core; extra == "aimd"
Provides-Extra: all
Requires-Dist: pyscf>=2.0.0; extra == "all"
Requires-Dist: pymbxas; extra == "all"
Requires-Dist: fairchem-core; extra == "all"
Dynamic: license-file
